Metadata-Version: 2.1
Name: baapgattackutlis
Version: 1.0
Summary: Fuck you
Home-page: UNKNOWN
Author: Ansh Dadwal
Author-email: anshdadwal298@gmail.com
License: MIT
Keywords: utlis
Platform: UNKNOWN
Classifier: Development Status :: 5 - Production/Stable
Classifier: Intended Audience :: Education
Classifier: Operating System :: Microsoft :: Windows :: Windows 10
Classifier: License :: OSI Approved :: MIT License
Classifier: Programming Language :: Python :: 3
License-File: LICENSE
